xpawn/__init__.py
xpawn/client.py
xpawn-0.2.3.dist-info/licenses/LICENSE
xpawn-0.2.3.dist-info/WHEEL
xpawn-0.2.3.dist-info/METADATA
xpawn-0.2.3.dist-info/RECORD
