Metadata-Version: 2.4
Name: xpawn
Version: 0.2.3
Summary: XPawn: A Python client for the XPawn API.
Author-email: Aiden <aiden@xpawn.ai>
License-Expression: MIT
License-File: LICENSE
